tableaudocumentapi/__init__.py
tableaudocumentapi/connection.py
tableaudocumentapi/datasource.py
tableaudocumentapi/dbclass.py
tableaudocumentapi/field.py
tableaudocumentapi/multilookup_dict.py
tableaudocumentapi/property_decorators.py
tableaudocumentapi/workbook.py
tableaudocumentapi/xfile.py
tableaudocumentapi-0.9.dist-info/LICENSE
tableaudocumentapi-0.9.dist-info/METADATA
tableaudocumentapi-0.9.dist-info/WHEEL
tableaudocumentapi-0.9.dist-info/top_level.txt
tableaudocumentapi-0.9.dist-info/RECORD
