Metadata-Version: 2.1
Name: tableaudocumentapi
Version: 0.9
Summary: A Python module for working with Tableau files.
Home-page: https://github.com/tableau/document-api-python
Author: Tableau
Author-email: github@tableau.com
License: MIT
Platform: UNKNOWN
